nipreps_versions-1.1.0.dist-info/METADATA
nipreps_versions-1.1.0.dist-info/WHEEL
nipreps_versions-1.1.0.dist-info/entry_points.txt
nipreps_versions-1.1.0.dist-info/licenses/LICENSE
nipreps_versions/__init__.py
nipreps_versions/schemes.py
nipreps_versions-1.1.0.dist-info/RECORD
