Metadata-Version: 2.4
Name: nipreps_versions
Version: 1.1.0
Summary: Version schemes for nipreps tools
Author-Email: Chris Markiewicz <markiewicz@stanford.edu>
License-Expression: Apache-2.0
Classifier: Development Status :: 5 - Production/Stable
Classifier: Intended Audience :: Developers
Classifier: Programming Language :: Python
Classifier: Programming Language :: Python :: 3
Classifier: Programming Language :: Python :: 3 :: Only
Classifier: Programming Language :: Python :: 3.10
Classifier: Programming Language :: Python :: 3.11
Classifier: Programming Language :: Python :: 3.12
Classifier: Programming Language :: Python :: 3.13
Classifier: Programming Language :: Python :: 3.14
Classifier: Topic :: Software Development :: Libraries
Classifier: Topic :: Software Development :: Version Control
Classifier: Topic :: System :: Software Distribution
Classifier: Topic :: Utilities
Project-URL: Home, https://github.com/nipreps/version-schemes
Project-URL: Nipreps, https://www.nipreps.org
Requires-Python: >=3.10
Requires-Dist: setuptools_scm>=7
Requires-Dist: packaging>=17
